README.rst
setup.py
editing/create_and_annotate_bed.py
editing/filter_known_snp.py
editing/filter_reads.py
editing/filter_variants.py
editing/rank_edits.py
rnaediting.egg-info/PKG-INFO
rnaediting.egg-info/SOURCES.txt
rnaediting.egg-info/dependency_links.txt
rnaediting.egg-info/requires.txt
rnaediting.egg-info/top_level.txt