Metadata-Version: 1.1
Name: rnaediting
Version: 0.0.7
Summary: Python scripts for filtering variant calls for finding rna editing specific events
Home-page: http://yeolab.github.io/
Author: Brian Yee
Author-email: bay001@ucsd.edu
License: MIT
Keywords: rna editing
Platform: UNKNOWN
Classifier: Development Status :: 3 - Alpha
Classifier: Intended Audience :: Developers
Classifier: Topic :: Software Development :: Build Tools
Classifier: License :: OSI Approved :: MIT License
Classifier: Programming Language :: Python :: 2
Classifier: Programming Language :: Python :: 2.6
Classifier: Programming Language :: Python :: 2.7
